adfin_interaction.py
api_importer.py
environment.py
filesystem.py
main_adfin_mcp.py
adfinmcp-0.1.1.dist-info/METADATA
adfinmcp-0.1.1.dist-info/WHEEL
adfinmcp-0.1.1.dist-info/entry_points.txt
adfinmcp-0.1.1.dist-info/top_level.txt
adfinmcp-0.1.1.dist-info/RECORD
