Metadata-Version: 2.4
Name: adfinmcp
Version: 0.1.1
Summary: An MCP server that interacts with all Adfin public APIs.
Requires-Python: >=3.12
Requires-Dist: mcp[cli]>=1.4.1
Requires-Dist: requests>=2.32.3
